dasl_api/__init__.py
dasl_api/api_client.py
dasl_api/api_response.py
dasl_api/configuration.py
dasl_api/exceptions.py
dasl_api/py.typed
dasl_api/rest.py
dasl_api/api/__init__.py
dasl_api/api/content_v1_api.py
dasl_api/api/core_v1_api.py
dasl_api/api/dbui_v1_api.py
dasl_api/api/workspace_v1_api.py
dasl_api/models/__init__.py
dasl_api/models/common_v1_job_meta.py
dasl_api/models/common_v1_list_meta.py
dasl_api/models/common_v1_object_meta.py
dasl_api/models/conflict_error.py
dasl_api/models/content_v1_datasource_preset.py
dasl_api/models/content_v1_datasource_preset_autoloader.py
dasl_api/models/content_v1_datasource_preset_autoloader_cloud_files.py
dasl_api/models/content_v1_datasource_preset_bronze.py
dasl_api/models/content_v1_datasource_preset_gold_inner.py
dasl_api/models/content_v1_datasource_preset_list.py
dasl_api/models/content_v1_datasource_preset_list_recommended_presets_inner.py
dasl_api/models/content_v1_datasource_preset_silver.py
dasl_api/models/content_v1_datasource_preset_silver_pre_transform_inner.py
dasl_api/models/content_v1_datasource_preset_silver_transform_inner.py
dasl_api/models/content_v1_datasource_preset_summary.py
dasl_api/models/content_v1_datasource_preset_version.py
dasl_api/models/content_v1_datasource_preset_version_list.py
dasl_api/models/content_v1_mitre_attack.py
dasl_api/models/content_v1_mitre_sub_technique.py
dasl_api/models/content_v1_mitre_tactic.py
dasl_api/models/content_v1_mitre_technique.py
dasl_api/models/content_v1_mitre_technique_detail.py
dasl_api/models/content_v1_preset_data_source_list.py
dasl_api/models/content_v1_preset_data_source_list_errors_inner.py
dasl_api/models/content_v1_preset_data_source_list_items_inner.py
dasl_api/models/content_v1_request_datasource_request.py
dasl_api/models/core_v1_data_source.py
dasl_api/models/core_v1_data_source_autoloader_spec.py
dasl_api/models/core_v1_data_source_field_spec.py
dasl_api/models/core_v1_data_source_field_spec_assert_inner.py
dasl_api-0.1.30.dist-info/METADATA
dasl_api-0.1.30.dist-info/WHEEL
dasl_api-0.1.30.dist-info/top_level.txt
dasl_api-0.1.30.dist-info/RECORD
