Metadata-Version: 2.1
Name: dasl-api
Version: 0.1.30
Summary: Lakewatch public API
Home-page: 
Author: OpenAPI Generator community
Author-email: support@antimatter.io
License: Apache-2.0
Keywords: OpenAPI,OpenAPI-Generator,Lakewatch public API
Requires-Dist: urllib3 <3.0.0,>=1.25.3
Requires-Dist: python-dateutil >=2.8.2
Requires-Dist: pydantic >=2
Requires-Dist: typing-extensions >=4.7.1
